{"data":{"deploymentLogs":[{"message":"⚠️ SENTRY_DSN not set. Error tracking disabled.","severity":"error","timestamp":"2026-02-11T00:09:43.986316608Z"},{"message":"⚠️  Escrow event handlers temporarily disabled","severity":"info","timestamp":"2026-02-11T00:09:43.986324855Z"},{"message":"✅ Deposit routes registered","severity":"info","timestamp":"2026-02-11T00:09:45.850301881Z"},{"message":"✅ Compliance monitoring routes registered","severity":"info","timestamp":"2026-02-11T00:09:45.850316896Z"},{"message":"Method 'GET' already declared for route '/precon/projects'","severity":"info","timestamp":"2026-02-11T00:09:45.850327398Z"},{"message":"✅ Environment detected: production","severity":"info","timestamp":"2026-02-11T00:09:47.882767904Z"},{"message":"[Tracing] Initialized for kealee-api (env: production)","severity":"info","timestamp":"2026-02-11T00:09:48.826681802Z"},{"message":"","severity":"info","timestamp":"2026-02-11T00:09:51.087193131Z"},{"message":"============================================================","severity":"info","timestamp":"2026-02-11T00:09:51.087209774Z"},{"message":"🚀 Environment Configuration 🚀","severity":"info","timestamp":"2026-02-11T00:09:51.087218379Z"},{"message":"============================================================","severity":"info","timestamp":"2026-02-11T00:09:51.087227097Z"},{"message":"Environment:        PRODUCTION","severity":"info","timestamp":"2026-02-11T00:09:51.087234784Z"},{"message":"APP_ENV:            (not set)","severity":"info","timestamp":"2026-02-11T00:09:51.087242631Z"},{"message":"NODE_ENV:           production","severity":"info","timestamp":"2026-02-11T00:09:51.087259390Z"},{"message":"Railway Env:        production","severity":"info","timestamp":"2026-02-11T00:09:51.087267528Z"},{"message":"Railway Service:    kealee-platform-v10","severity":"info","timestamp":"2026-02-11T00:09:51.087274531Z"},{"message":"Is Production:      true","severity":"info","timestamp":"2026-02-11T00:09:51.087283560Z"},{"message":"Is Staging:         false","severity":"info","timestamp":"2026-02-11T00:09:51.087293543Z"},{"message":"Is Preview:         false","severity":"info","timestamp":"2026-02-11T00:09:51.087300645Z"},{"message":"Is Development:     false","severity":"info","timestamp":"2026-02-11T00:09:51.087308170Z"},{"message":"============================================================","severity":"info","timestamp":"2026-02-11T00:09:51.087317887Z"},{"message":"","severity":"info","timestamp":"2026-02-11T00:09:51.087325341Z"},{"message":"⚠️  Warning: STRIPE_SECRET_KEY does not match production pattern in production environment","severity":"error","timestamp":"2026-02-11T00:09:51.087332484Z"},{"message":"⚠️  Warning: STRIPE_PUBLISHABLE_KEY does not match production pattern in production environment","severity":"error","timestamp":"2026-02-11T00:09:51.087339915Z"},{"message":"⚠️ SENTRY_DSN not set. Error tracking disabled.","severity":"error","timestamp":"2026-02-11T00:09:51.087347575Z"},{"message":"⚠️  Escrow event handlers temporarily disabled","severity":"info","timestamp":"2026-02-11T00:09:51.087354614Z"},{"message":"✅ Deposit routes registered","severity":"info","timestamp":"2026-02-11T00:09:51.087363635Z"},{"message":"✅ Compliance monitoring routes registered","severity":"info","timestamp":"2026-02-11T00:09:51.978894711Z"},{"message":"Method 'GET' already declared for route '/precon/projects'","severity":"info","timestamp":"2026-02-11T00:09:51.978902563Z"},{"message":"✅ Environment detected: production","severity":"info","timestamp":"2026-02-11T00:09:54.245658864Z"},{"message":"[Tracing] Initialized for kealee-api (env: production)","severity":"info","timestamp":"2026-02-11T00:09:54.245666105Z"},{"message":"","severity":"info","timestamp":"2026-02-11T00:09:57.045270457Z"},{"message":"============================================================","severity":"info","timestamp":"2026-02-11T00:09:57.045280026Z"},{"message":"🚀 Environment Configuration 🚀","severity":"info","timestamp":"2026-02-11T00:09:57.045288985Z"},{"message":"============================================================","severity":"info","timestamp":"2026-02-11T00:09:57.045298599Z"},{"message":"Environment:        PRODUCTION","severity":"info","timestamp":"2026-02-11T00:09:57.045310131Z"},{"message":"APP_ENV:            (not set)","severity":"info","timestamp":"2026-02-11T00:09:57.045504503Z"},{"message":"NODE_ENV:           production","severity":"info","timestamp":"2026-02-11T00:09:57.045511992Z"},{"message":"Railway Env:        production","severity":"info","timestamp":"2026-02-11T00:09:57.045521288Z"},{"message":"Railway Service:    kealee-platform-v10","severity":"info","timestamp":"2026-02-11T00:09:57.045528703Z"},{"message":"Is Production:      true","severity":"info","timestamp":"2026-02-11T00:09:57.045537060Z"},{"message":"Is Staging:         false","severity":"info","timestamp":"2026-02-11T00:09:57.045545170Z"},{"message":"Is Preview:         false","severity":"info","timestamp":"2026-02-11T00:09:57.045553352Z"},{"message":"Is Development:     false","severity":"info","timestamp":"2026-02-11T00:09:57.045561804Z"},{"message":"============================================================","severity":"info","timestamp":"2026-02-11T00:09:57.045570210Z"},{"message":"","severity":"info","timestamp":"2026-02-11T00:09:57.045577670Z"},{"message":"⚠️  Warning: STRIPE_SECRET_KEY does not match production pattern in production environment","severity":"error","timestamp":"2026-02-11T00:09:57.045585397Z"},{"message":"⚠️  Warning: STRIPE_PUBLISHABLE_KEY does not match production pattern in production environment","severity":"error","timestamp":"2026-02-11T00:09:57.045592635Z"},{"message":"⚠️ SENTRY_DSN not set. Error tracking disabled.","severity":"error","timestamp":"2026-02-11T00:09:57.045599375Z"},{"message":"⚠️  Escrow event handlers temporarily disabled","severity":"info","timestamp":"2026-02-11T00:09:57.045613953Z"},{"message":"✅ Deposit routes registered","severity":"info","timestamp":"2026-02-11T00:09:59.005141841Z"},{"message":"✅ Compliance monitoring routes registered","severity":"info","timestamp":"2026-02-11T00:09:59.005150701Z"},{"message":"Method 'GET' already declared for route '/precon/projects'","severity":"info","timestamp":"2026-02-11T00:09:59.005156904Z"},{"message":"✅ Environment detected: production","severity":"info","timestamp":"2026-02-11T00:10:00.961923306Z"},{"message":"[Tracing] Initialized for kealee-api (env: production)","severity":"info","timestamp":"2026-02-11T00:10:00.961933539Z"},{"message":"","severity":"info","timestamp":"2026-02-11T00:10:04.426424472Z"},{"message":"============================================================","severity":"info","timestamp":"2026-02-11T00:10:04.426433466Z"},{"message":"🚀 Environment Configuration 🚀","severity":"info","timestamp":"2026-02-11T00:10:04.426442899Z"},{"message":"============================================================","severity":"info","timestamp":"2026-02-11T00:10:04.427452246Z"},{"message":"Environment:        PRODUCTION","severity":"info","timestamp":"2026-02-11T00:10:04.427485088Z"},{"message":"APP_ENV:            (not set)","severity":"info","timestamp":"2026-02-11T00:10:04.427491977Z"},{"message":"NODE_ENV:           production","severity":"info","timestamp":"2026-02-11T00:10:04.427500414Z"},{"message":"Railway Env:        production","severity":"info","timestamp":"2026-02-11T00:10:04.427507108Z"},{"message":"Railway Service:    kealee-platform-v10","severity":"info","timestamp":"2026-02-11T00:10:04.427513957Z"},{"message":"Is Production:      true","severity":"info","timestamp":"2026-02-11T00:10:04.427520420Z"},{"message":"Is Staging:         false","severity":"info","timestamp":"2026-02-11T00:10:04.427526848Z"},{"message":"Is Preview:         false","severity":"info","timestamp":"2026-02-11T00:10:04.427533190Z"},{"message":"Is Development:     false","severity":"info","timestamp":"2026-02-11T00:10:04.427539963Z"},{"message":"============================================================","severity":"info","timestamp":"2026-02-11T00:10:04.427546210Z"},{"message":"","severity":"info","timestamp":"2026-02-11T00:10:04.427552578Z"},{"message":"⚠️  Warning: STRIPE_SECRET_KEY does not match production pattern in production environment","severity":"error","timestamp":"2026-02-11T00:10:04.427559560Z"},{"message":"⚠️  Warning: STRIPE_PUBLISHABLE_KEY does not match production pattern in production environment","severity":"error","timestamp":"2026-02-11T00:10:04.427565328Z"},{"message":"⚠️ SENTRY_DSN not set. Error tracking disabled.","severity":"error","timestamp":"2026-02-11T00:10:04.427571699Z"},{"message":"⚠️  Escrow event handlers temporarily disabled","severity":"info","timestamp":"2026-02-11T00:10:04.427578200Z"},{"message":"✅ Deposit routes registered","severity":"info","timestamp":"2026-02-11T00:10:04.427586308Z"},{"message":"✅ Compliance monitoring routes registered","severity":"info","timestamp":"2026-02-11T00:10:06.367153400Z"},{"message":"Method 'GET' already declared for route '/precon/projects'","severity":"info","timestamp":"2026-02-11T00:10:06.367160790Z"},{"message":"✅ Environment detected: production","severity":"info","timestamp":"2026-02-11T00:10:08.135361402Z"},{"message":"[Tracing] Initialized for kealee-api (env: production)","severity":"info","timestamp":"2026-02-11T00:10:10.295545908Z"},{"message":"============================================================","severity":"info","timestamp":"2026-02-11T00:10:13.190362431Z"},{"message":"","severity":"info","timestamp":"2026-02-11T00:10:13.190377969Z"},{"message":"","severity":"info","timestamp":"2026-02-11T00:10:13.190381886Z"},{"message":"⚠️  Warning: STRIPE_SECRET_KEY does not match production pattern in production environment","severity":"error","timestamp":"2026-02-11T00:10:13.190388412Z"},{"message":"============================================================","severity":"info","timestamp":"2026-02-11T00:10:13.190393038Z"},{"message":"⚠️  Warning: STRIPE_PUBLISHABLE_KEY does not match production pattern in production environment","severity":"error","timestamp":"2026-02-11T00:10:13.190398247Z"},{"message":"⚠️ SENTRY_DSN not set. Error tracking disabled.","severity":"error","timestamp":"2026-02-11T00:10:13.190405384Z"},{"message":"⚠️  Escrow event handlers temporarily disabled","severity":"info","timestamp":"2026-02-11T00:10:13.190431156Z"},{"message":"✅ Deposit routes registered","severity":"info","timestamp":"2026-02-11T00:10:13.190439194Z"},{"message":"🚀 Environment Configuration 🚀","severity":"info","timestamp":"2026-02-11T00:10:13.190550127Z"},{"message":"============================================================","severity":"info","timestamp":"2026-02-11T00:10:13.190557638Z"},{"message":"Environment:        PRODUCTION","severity":"info","timestamp":"2026-02-11T00:10:13.190566165Z"},{"message":"Is Production:      true","severity":"info","timestamp":"2026-02-11T00:10:13.190601418Z"},{"message":"Is Staging:         false","severity":"info","timestamp":"2026-02-11T00:10:13.190611743Z"},{"message":"Is Preview:         false","severity":"info","timestamp":"2026-02-11T00:10:13.190620378Z"},{"message":"Is Development:     false","severity":"info","timestamp":"2026-02-11T00:10:13.190627736Z"},{"message":"APP_ENV:            (not set)","severity":"info","timestamp":"2026-02-11T00:10:13.190632585Z"},{"message":"NODE_ENV:           production","severity":"info","timestamp":"2026-02-11T00:10:13.190640947Z"},{"message":"Railway Env:        production","severity":"info","timestamp":"2026-02-11T00:10:13.190647711Z"},{"message":"Railway Service:    kealee-platform-v10","severity":"info","timestamp":"2026-02-11T00:10:13.190654709Z"},{"message":"✅ Compliance monitoring routes registered","severity":"info","timestamp":"2026-02-11T00:10:15.078005345Z"},{"message":"Method 'GET' already declared for route '/precon/projects'","severity":"info","timestamp":"2026-02-11T00:10:15.078037734Z"}]}}
